zarr_checksum/__init__.py
zarr_checksum/checksum.py
zarr_checksum/cli.py
zarr_checksum/generators.py
zarr_checksum/py.typed
zarr_checksum/tests/__init__.py
zarr_checksum/tests/conftest.py
zarr_checksum/tests/test_checksum.py
zarr_checksum/tests/test_generators.py
zarr_checksum/tests/test_tree.py
zarr_checksum/tree.py
zarr_checksum-0.4.6.dist-info/LICENSE
zarr_checksum-0.4.6.dist-info/METADATA
zarr_checksum-0.4.6.dist-info/NOTICE
zarr_checksum-0.4.6.dist-info/WHEEL
zarr_checksum-0.4.6.dist-info/entry_points.txt
zarr_checksum-0.4.6.dist-info/RECORD
