Metadata-Version: 2.3
Name: zarr-checksum
Version: 0.4.6
Summary: Checksum support for zarrs stored in various backends
License: Apache-2.0
Author: Kitware, Inc.
Author-email: kitware@kitware.com
Requires-Python: >=3.7
Classifier: License :: OSI Approved :: Apache Software License
Classifier: Programming Language :: Python :: 3
Classifier: Programming Language :: Python :: 3.7
Classifier: Programming Language :: Python :: 3.8
Classifier: Programming Language :: Python :: 3.9
Classifier: Programming Language :: Python :: 3.10
Classifier: Programming Language :: Python :: 3.11
Classifier: Programming Language :: Python :: 3.12
Classifier: Programming Language :: Python :: 3.13
Provides-Extra: boto
Provides-Extra: dev
Provides-Extra: format
Provides-Extra: lint
Provides-Extra: test
Provides-Extra: zarr
Requires-Dist: boto3 (>=1.24) ; extra == "boto"
Requires-Dist: boto3-stubs (>=1.24) ; extra == "dev"
Requires-Dist: click (>=8.1.8)
Requires-Dist: faker ; extra == "test"
Requires-Dist: minio ; extra == "test"
Requires-Dist: pytest (>=7.2.1) ; extra == "test"
Requires-Dist: ruff (>=0.11.2) ; extra == "dev"
Requires-Dist: ruff (>=0.11.2) ; extra == "format"
Requires-Dist: ruff (>=0.11.2) ; extra == "lint"
Requires-Dist: tqdm (>=4.67.1)
Requires-Dist: zarr (>=2.12,<3) ; extra == "zarr"
Project-URL: Homepage, https://github.com/dandi/zarr_checksum
Project-URL: Repository, https://github.com/dandi/zarr_checksum
